jrender/__init__.py
jrender/cli.py
jrender-1.1.dist-info/METADATA
jrender-1.1.dist-info/WHEEL
jrender-1.1.dist-info/entry_points.txt
jrender-1.1.dist-info/RECORD
